sswater/GAILinear.py
sswater/NLinear.py
sswater/__init__.py
sswater/calData.py
sswater/config.py
sswater/create_seq.py
sswater/getDatas.py
sswater/models.py
sswater/preprocessing.py
sswater/serializers.py
sswater/services.py
sswater/train.py
sswater-0.0.5.dist-info/METADATA
sswater-0.0.5.dist-info/WHEEL
sswater-0.0.5.dist-info/top_level.txt
sswater-0.0.5.dist-info/RECORD
